setup.py
django_restroom.egg-info/PKG-INFO
django_restroom.egg-info/SOURCES.txt
django_restroom.egg-info/dependency_links.txt
django_restroom.egg-info/requires.txt
django_restroom.egg-info/top_level.txt
restroom/__init__.py
restroom/constants.py
restroom/core.py
restroom/errors.py
restroom/models.py
restroom/resources.py
restroom/utils.py
restroom/views.py