Metadata-Version: 1.0
Name: django-restroom
Version: 0.0.2
Summary: Super lightweight REST API framework for Django
Home-page: https://github.com/suneel0101/django-restroom
Author: Suneel Chakravorty
Author-email: suneel0101@gmail.com.com
License: UNKNOWN
Platform: UNKNOWN
